{
  "questionId": "0x754c4e18102a5e873f88a5111ba979bbda8ff6935c7546aedb6b8d8e4d7f17ea",
  "title": "In season 004, Which proposal will pass and finished in time?",
  "outcomes": [
    {
      "title": "DCP-1: Project cover",
      "short": "DCP-1"
    },
    {
      "title": "DCP-2: Tools develop",
      "short": "DCP-2"
    },
    {
      "title": "DCP-3: Tools develop",
      "short": "DCP-3"
    },
    {
      "title": "DCP-4: Tools develop",
      "short": "DCP-4"
    },
    {
      "title": "DCP-5: Project cover",
      "short": "DCP-5"
    },
    {
      "title": "DCP-6: Tools develop",
      "short": "DCP-6"
    },
    {
      "title": "DCP-7: Tools develop",
      "short": "DCP-7"
    },
    {
      "title": "DCP-8: Tools develop",
      "short": "DCP-8"
    }
  ]
}